MANIFEST.in
README.md
setup.py
bum/__init__.py
bum/__main__.py
bum/brainz.py
bum/display.py
bum/song.py
bum/util.py
bum.egg-info/PKG-INFO
bum.egg-info/SOURCES.txt
bum.egg-info/dependency_links.txt
bum.egg-info/entry_points.txt
bum.egg-info/requires.txt
bum.egg-info/top_level.txt